lacrei_models/__init__.py
lacrei_models/address/models.py
lacrei_models/appointments/models.py
lacrei_models/appointments/utils.py
lacrei_models/lacreiid/adapters.py
lacrei_models/lacreiid/managers.py
lacrei_models/lacreiid/models.py
lacrei_models/lacreiid/template_context_models.py
lacrei_models/lacreisaude/constants.py
lacrei_models/lacreisaude/managers.py
lacrei_models/lacreisaude/models.py
lacrei_models/lacreisaude/services/__init__.py
lacrei_models/lacreisaude/services/constants.py
lacrei_models/lacreisaude/services/exceptions.py
lacrei_models/lacreisaude/services/verification.py
lacrei_models/lacreisaude/template_context_models.py
lacrei_models/notification/exceptions.py
lacrei_models/notification/models.py
lacrei_models/notification/services.py
lacrei_models/notification/signals.py
lacrei_models/notification/template_context_models.py
lacrei_models/notification/utils.py
lacrei_models/payments/clients/asaas.py
lacrei_models/payments/clients/brasil_api.py
lacrei_models/payments/models.py
lacrei_models/payments/tasks.py
lacrei_models/payments/types.py
lacrei_models/sync/models.py
lacrei_models/utils/__init__.py
lacrei_models/utils/constants.py
lacrei_models/utils/email_verifier.py
lacrei_models/utils/models.py
lacrei_models/utils/sites.py
lacrei_models/utils/template_context_models.py
lacrei_models/utils/validators.py
lacrei_models2-0.1.2.dist-info/METADATA
lacrei_models2-0.1.2.dist-info/WHEEL
lacrei_models2-0.1.2.dist-info/RECORD
